second_python_package/__init__.py
second_python_package/harmonic_mean.pyi
second_python_package/harmonic_mean.pyx
second_python_package/harmony.py
second_python_package/py.typed
second_python_package/harmonic_mean.cpython-310-darwin.so
second_python_package/harmonic_mean.c
pubpypack_harmony_tpotjj-0.1.0.dist-info/WHEEL
pubpypack_harmony_tpotjj-0.1.0.dist-info/entry_points.txt
pubpypack_harmony_tpotjj-0.1.0.dist-info/METADATA
pubpypack_harmony_tpotjj-0.1.0.dist-info/RECORD
